xarm7_ik/__init__.py
xarm7_ik/kinematics.py
xarm7_ik/solver.py
xarm7_ik/utils.py
xarm7_ik-0.3.2.dist-info/METADATA
xarm7_ik-0.3.2.dist-info/WHEEL
xarm7_ik-0.3.2.dist-info/top_level.txt
xarm7_ik-0.3.2.dist-info/RECORD
