Metadata-Version: 2.4
Name: xarm7-ik
Version: 0.3.2
Summary: A fast inverse kinematics (IK) solver for xArm7 with/without the linear rail and base rotation offset support
Requires-Python: >=3.10
Requires-Dist: nlopt>=2.9.1
Requires-Dist: numba>=0.61.2
Requires-Dist: scipy>=1.15.3
Provides-Extra: examples
Requires-Dist: mujoco>=3.3.5; extra == "examples"
